wordsprobability/__init__.py
wordsprobability/main.py
wordsprobability/models/__init__.py
wordsprobability/models/bow_lm.py
wordsprobability/utils/__init__.py
wordsprobability/utils/constants.py
wordsprobability/utils/utils.py
wordsprobability-0.17.dist-info/LICENSE
wordsprobability-0.17.dist-info/METADATA
wordsprobability-0.17.dist-info/WHEEL
wordsprobability-0.17.dist-info/entry_points.txt
wordsprobability-0.17.dist-info/top_level.txt
wordsprobability-0.17.dist-info/RECORD
