Metadata-Version: 2.1
Name: wordsprobability
Version: 0.17
Summary: Method to get a words probability with fixes from How to Compute the Probability of a Word.
Home-page: https://github.com/tpimentelms/probability-of-a-word
Author: Tiago Pimentel and Clara Meister
Author-email: tpimentelms@gmail.com
License: MIT
Keywords: language modelling surprisal word tokenisation probability
License-File: LICENSE
Requires-Dist: torch
Requires-Dist: transformers
Requires-Dist: pandas
